jysnowball/__init__.py
jysnowball/api_ref.py
jysnowball/bond.py
jysnowball/capital.py
jysnowball/cons.py
jysnowball/cube.py
jysnowball/f10.py
jysnowball/finance.py
jysnowball/fund.py
jysnowball/hkex.py
jysnowball/index.py
jysnowball/realtime.py
jysnowball/report.py
jysnowball/token.py
jysnowball/user.py
jysnowball/utls.py
tests/__init__.py
jysnowball-0.3.0.dist-info/METADATA
jysnowball-0.3.0.dist-info/WHEEL
jysnowball-0.3.0.dist-info/top_level.txt
jysnowball-0.3.0.dist-info/RECORD
