Metadata-Version: 2.1
Name: jysnowball
Version: 0.3.0
Summary: A brief description of your package
Home-page: https://github.com/yzw2010/jysnowball/
Author: JY Yu Chi Wai
Author-email: qq13715416@gmail.com
License: UNKNOWN
Platform: UNKNOWN
Classifier: Programming Language :: Python :: 3
Classifier: License :: OSI Approved :: MIT License
Classifier: Operating System :: OS Independent
Requires-Python: >=3.6
